{
    "美图秀秀": "meitu.com",
    "B612咔叽": "b612.net",
    "轻颜相机": "qingyan.com",
    "Facetune": "facetune.com",
    "无他相机": "wuta-cam.com",
    "美颜相机": "meiyan.com",
    "天天P图": "ttpic.qq.com",
    "Retrica": "retrica.co",
    "Ulike": "ulikecam.com",
    "美图相机": "camera.meitu.com",
    "潮自拍": "chaozp.com",
    "BeautyCam": "beautycam.com",
    "Foodie": "foodie.com",
    "SNOW相机": "snow.me",
    "Snapchat": "snapchat.com",
    "Instagram": "instagram.com",
    "VSCO": "vsco.co",
    "Snapseed": "snapseed.online",
    "Lightroom": "lightroom.adobe.com",
    "泼辣修图": "polarr.co",
    "Prisma": "prisma-ai.com",
    "Pixlr": "pixlr.com",
    "PicsArt": "picsart.com",
    "Canva": "canva.com",
    "Fotor": "fotor.com",
    "Photoshop Express": "photoshop.com",
    "Afterlight": "afterlight.us",
    "Enlight": "enlightapp.com",
    "Camera360": "camera360.com",